[
  {
    "name": "Hines",
    "surname": "Rodgers",
    "address": "592 Chase Court",
    "city": "Rivera"
  },
  {
    "name": "Whitley",
    "surname": "Gonzales",
    "address": "542 Mayfair Drive",
    "city": "Kanauga"
  },
  {
    "name": "Mcclain",
    "surname": "Livingston",
    "address": "955 Woodhull Street",
    "city": "Linganore"
  },
  {
    "name": "Consuelo",
    "surname": "Nash",
    "address": "606 Commercial Street",
    "city": "Leola"
  },
  {
    "name": "Harriet",
    "surname": "Reynolds",
    "address": "663 Cox Place",
    "city": "Deltaville"
  },
  {
    "name": "Claudia",
    "surname": "Lewis",
    "address": "478 Anchorage Place",
    "city": "Bordelonville"
  },
  {
    "name": "Ronda",
    "surname": "Gardner",
    "address": "448 Virginia Place",
    "city": "Alleghenyville"
  },
  {
    "name": "Barbara",
    "surname": "Salas",
    "address": "579 McKinley Avenue",
    "city": "Fidelis"
  },
  {
    "name": "Bridges",
    "surname": "Moody",
    "address": "568 Beach Place",
    "city": "Dixonville"
  },
  {
    "name": "Josie",
    "surname": "Wiggins",
    "address": "706 Hart Street",
    "city": "Callaghan"
  },
  {
    "name": "Newton",
    "surname": "Oconnor",
    "address": "214 Ocean Avenue",
    "city": "Crayne"
  },
  {
    "name": "Hill",
    "surname": "Pitts",
    "address": "160 Grimes Road",
    "city": "Blairstown"
  },
  {
    "name": "Erickson",
    "surname": "Simmons",
    "address": "294 Batchelder Street",
    "city": "Oberlin"
  },
  {
    "name": "Tamika",
    "surname": "Bray",
    "address": "337 Brighton Court",
    "city": "Waiohinu"
  },
  {
    "name": "Gay",
    "surname": "Carrillo",
    "address": "507 Hillel Place",
    "city": "Oceola"
  },
  {
    "name": "Ryan",
    "surname": "Guerrero",
    "address": "310 Ross Street",
    "city": "Hendersonville"
  },
  {
    "name": "Cervantes",
    "surname": "Riley",
    "address": "314 Montauk Avenue",
    "city": "Vandiver"
  },
  {
    "name": "Barlow",
    "surname": "Mayer",
    "address": "869 Kenilworth Place",
    "city": "Jacksonwald"
  },
  {
    "name": "Benson",
    "surname": "Mercado",
    "address": "184 Hendrix Street",
    "city": "Cawood"
  },
  {
    "name": "Sparks",
    "surname": "Lang",
    "address": "488 Gotham Avenue",
    "city": "Stewart"
  }
]